{
  "kind": "books#volumes",
  "totalItems": 1,
  "items": [
    {
      "kind": "books#volume",
      "id": "8CpIngEACAAJ",
      "etag": "BQ2CIvDg140",
      "selfLink": "https://www.googleapis.com/books/v1/volumes/8CpIngEACAAJ",
      "volumeInfo": {
        "title": "A Storm of Swords",
        "authors": [
          "George R. R. Martin"
        ],
        "publishedDate": "2013-12-01",
        "description": "Winter approaches Westeros like an angry beast. The Seven Kingdoms are divided by revolt and blood feud. In the northern wastes, a horde of hungry, savage people steeped in the dark magic of the wilderness is poised to invade the Kingdom of the North where Robb Stark wears his new-forged crown. And Robb's defences are ranged against the South, the land of the cunning and cruel Lannisters, who have his younger sisters in their power. Throughout Westeros, the war for the Iron Throne rages more fiercely than ever, but if the Wall is breached, no king will live to claim it.",
        "industryIdentifiers": [
          {
            "type": "ISBN_10",
            "identifier": "0007548257"
          },
          {
            "type": "ISBN_13",
            "identifier": "9780007548255"
          }
        ],
        "readingModes": {
          "text": false,
          "image": false
        },
        "pageCount": 623,
        "printType": "BOOK",
        "categories": [
          "Fiction"
        ],
        "maturityRating": "NOT_MATURE",
        "allowAnonLogging": false,
        "contentVersion": "preview-1.0.0",
        "imageLinks": {
          "smallThumbnail": "http://books.google.com/books/content?id=8CpIngEACAAJ&printsec=frontcover&img=1&zoom=5&source=gbs_api",
          "thumbnail": "http://books.google.com/books/content?id=8CpIngEACAAJ&printsec=frontcover&img=1&zoom=1&source=gbs_api"
        },
        "language": "en",
        "previewLink": "http://books.google.com/books?id=8CpIngEACAAJ&dq=A_Storm_of_Swords+inauthor:martin+isbn:9780007548255&hl=&cd=1&source=gbs_api",
        "infoLink": "http://books.google.com/books?id=8CpIngEACAAJ&dq=A_Storm_of_Swords+inauthor:martin+isbn:9780007548255&hl=&source=gbs_api",
        "canonicalVolumeLink": "https://books.google.com/books/about/A_Storm_of_Swords.html?hl=&id=8CpIngEACAAJ"
      },
      "saleInfo": {
        "country": "US",
        "saleability": "NOT_FOR_SALE",
        "isEbook": false
      },
      "accessInfo": {
        "country": "US",
        "viewability": "NO_PAGES",
        "embeddable": false,
        "publicDomain": false,
        "textToSpeechPermission": "ALLOWED",
        "epub": {
          "isAvailable": false
        },
        "pdf": {
          "isAvailable": false
        },
        "webReaderLink": "http://play.google.com/books/reader?id=8CpIngEACAAJ&hl=&source=gbs_api",
        "accessViewStatus": "NONE",
        "quoteSharingAllowed": false
      },
      "searchInfo": {
        "textSnippet": "The Seven Kingdoms are divided by revolt and blood feud."
      }
    }
  ]
}
